cbinterface/__init__.py
cbinterface/cli.py
cbinterface/commands.py
cbinterface/config.py
cbinterface/enterprise_edr/__init__.py
cbinterface/enterprise_edr/cli.py
cbinterface/enterprise_edr/device.py
cbinterface/enterprise_edr/enumerations.py
cbinterface/enterprise_edr/intel.py
cbinterface/enterprise_edr/process.py
cbinterface/enterprise_edr/query.py
cbinterface/enterprise_edr/sessions.py
cbinterface/enterprise_edr/ubs.py
cbinterface/helpers.py
cbinterface/playbook_configs/collect_browsing_history.ini
cbinterface/playbook_configs/collect_scheduled_tasks.ini
cbinterface/playbook_configs/delete_directory.ini
cbinterface/playbook_configs/delete_scheduled_task.ini
cbinterface/playbook_configs/delete_service.ini
cbinterface/playbook_configs/force_restart.ini
cbinterface/response/cli.py
cbinterface/response/enumerations.py
cbinterface/response/process.py
cbinterface/response/query.py
cbinterface/response/sensor.py
cbinterface/response/sessions.py
cbinterface/response/watchlists.py
cbinterface/scripted_live_response.py
cbinterface/templates/playbook.ini
cbinterface/templates/remediate.ini
cbinterface/tools/chromium_history_parser.py
cbinterface/tools/get_chromium_browsing_data.bat
cbinterface-3.0.10.dist-info/METADATA
cbinterface-3.0.10.dist-info/WHEEL
cbinterface-3.0.10.dist-info/licenses/LICENSE
cbinterface-3.0.10.dist-info/RECORD
