Metadata-Version: 2.4
Name: cbinterface
Version: 3.0.10
Summary: command line tool for interfacing with multiple carbonblack environments to perform analysis and live response functions
License: LICENSE
License-File: LICENSE
Keywords: Carbon Black,carbonblack
Author: Sean McFeely
Author-email: mcfeelynaes@gmail.com
Requires-Python: >=3.6,<4.0
Classifier: License :: Other/Proprietary License
Classifier: Programming Language :: Python :: 3
Classifier: Programming Language :: Python :: 3.6
Classifier: Programming Language :: Python :: 3.7
Classifier: Programming Language :: Python :: 3.8
Classifier: Programming Language :: Python :: 3.9
Classifier: Programming Language :: Python :: 3.10
Classifier: Programming Language :: Python :: 3.11
Classifier: Programming Language :: Python :: 3.12
Classifier: Programming Language :: Python :: 3.13
Classifier: Programming Language :: Python :: 3.14
Requires-Dist: argcomplete (==2.*)
Requires-Dist: carbon-black-cloud-sdk (>=1.5,<2.0)
Requires-Dist: cbapi (>=1.7.3,<2.0.0)
Requires-Dist: coloredlogs (>=15.0,<16.0)
Project-URL: Homepage, https://github.com/ace-ecosystem/cbinterface2
